molspecutils/__init__.py
molspecutils/happier.py
molspecutils/hitran.py
molspecutils/mirs.py
molspecutils/molecule.py
molspecutils/py.typed
molspecutils/utils.py
molspecutils/alchemy/C2H2_nu1nu3.py
molspecutils/alchemy/CH3Cl_nu3.py
molspecutils/alchemy/CO.py
molspecutils/alchemy/__init__.py
molspecutils/alchemy/convert.py
molspecutils/alchemy/meta.py
molspecutils/data/__init__.py
molspecutils/data/pytips.py
molspecutils/foreign/__init__.py
molspecutils/foreign/hapi3.py
molspecutils-0.3.1.dist-info/LICENSE
molspecutils-0.3.1.dist-info/METADATA
molspecutils-0.3.1.dist-info/WHEEL
molspecutils-0.3.1.dist-info/top_level.txt
molspecutils-0.3.1.dist-info/RECORD
