Metadata-Version: 2.1
Name: molspecutils
Version: 0.3.1
Summary: Modules for working with molecular spectroscopy data
Home-page: https://github.com/gkowzan/molspecutils
Author: Grzegorz Kowzan
Author-email: gkowzan@umk.pl
License: MIT License
Classifier: Development Status :: 4 - Beta
Classifier: Environment :: Console
Classifier: Intended Audience :: Science/Research
Classifier: Topic :: Scientific/Engineering :: Physics
Classifier: Programming Language :: Python :: 3
Classifier: Programming Language :: Python :: 3.6
Classifier: Programming Language :: Python :: 3.7
Classifier: Programming Language :: Python :: 3.8
Classifier: Programming Language :: Python :: 3.9
Classifier: Programming Language :: Python :: 3.10
Classifier: Topic :: Scientific/Engineering :: Physics
Classifier: Topic :: Scientific/Engineering :: Chemistry
Classifier: Typing :: Typed
Classifier: License :: OSI Approved :: MIT License
Requires-Python: >=3.6
License-File: LICENSE
Requires-Dist: attrs (>=21.4.0)
Requires-Dist: numpy (>=1.16.5)
Requires-Dist: scipy (>=1.3)
Requires-Dist: appdirs (>=1.4.4)
Requires-Dist: SQLAlchemy (>=1.4.6)
Provides-Extra: doc
Requires-Dist: Sphinx ; extra == 'doc'
Requires-Dist: sphinx-book-theme ; extra == 'doc'
